plato/__init__.py
plato/api.py
plato/constants.py
plato/main.py
plato_rag-0.0.4.dist-info/LICENSE
plato_rag-0.0.4.dist-info/METADATA
plato_rag-0.0.4.dist-info/WHEEL
plato_rag-0.0.4.dist-info/entry_points.txt
plato_rag-0.0.4.dist-info/top_level.txt
plato_rag-0.0.4.dist-info/RECORD
