Metadata-Version: 2.1
Name: plato_rag
Version: 0.0.4
License-File: LICENSE
Requires-Dist: requests
